[{
  "_id": {
    "$oid": "68e7f12708b0ee7b2d1b2fc0"
  },
  "name": "1",
  "manager": "Василинин Алексей Васильевич",
  "district": "СЗАО, ЗелАО",
  "phones": [
    {
      "name": "Руководитель",
      "number": "+7 (499) 493-31-79",
      "_id": {
        "$oid": "68e7f3a308b0ee7b2d1b337f"
      }
    }
  ],
  "createdAt": {
    "$date": "2025-10-09T17:30:15.646Z"
  },
  "updatedAt": {
    "$date": "2025-10-09T17:40:51.769Z"
  },
  "__v": 0
},
{
  "_id": {
    "$oid": "68e7f15e08b0ee7b2d1b2fea"
  },
  "name": "2",
  "manager": "Коровин Михаил Юрьевич",
  "district": "САО",
  "phones": [
    {
      "name": "Руководитель",
      "number": "+7 (499) 206-00-11",
      "_id": {
        "$oid": "68e7f3af08b0ee7b2d1b338b"
      }
    }
  ],
  "createdAt": {
    "$date": "2025-10-09T17:31:10.079Z"
  },
  "updatedAt": {
    "$date": "2025-10-09T17:41:03.956Z"
  },
  "__v": 0
},
{
  "_id": {
    "$oid": "68e7f32508b0ee7b2d1b333f"
  },
  "name": "3",
  "manager": "Данилов Евгений Юрьевич",
  "district": "СВАО",
  "phones": [
    {
      "name": "Руководитель",
      "number": "+7 (495) 620-52-59",
      "_id": {
        "$oid": "68e7f32508b0ee7b2d1b3340"
      }
    }
  ],
  "createdAt": {
    "$date": "2025-10-09T17:38:46.002Z"
  },
  "updatedAt": {
    "$date": "2025-10-09T17:38:46.002Z"
  },
  "__v": 0
},
{
  "_id": {
    "$oid": "68e7f33a08b0ee7b2d1b334a"
  },
  "name": "4",
  "manager": "Тобратова Жанна Николаевна",
  "district": "ВАО",
  "phones": [
    {
      "name": "Руководитель",
      "number": "+7 (499) 164-09-03",
      "_id": {
        "$oid": "68e7f3bb08b0ee7b2d1b3397"
      }
    }
  ],
  "createdAt": {
    "$date": "2025-10-09T17:39:06.169Z"
  },
  "updatedAt": {
    "$date": "2025-10-09T17:41:15.048Z"
  },
  "__v": 0
},
{
  "_id": {
    "$oid": "68e7f37508b0ee7b2d1b3368"
  },
  "name": "5",
  "manager": "Исаев Дмитрий Валерьевич",
  "district": "ЮВАО",
  "phones": [
    {
      "name": "Руководитель",
      "number": "+7 (495) 349-79-93",
      "_id": {
        "$oid": "68e7f3c408b0ee7b2d1b33a3"
      }
    }
  ],
  "createdAt": {
    "$date": "2025-10-09T17:40:05.905Z"
  },
  "updatedAt": {
    "$date": "2025-10-09T17:41:24.758Z"
  },
  "__v": 0
},
{
  "_id": {
    "$oid": "68e7f39308b0ee7b2d1b3373"
  },
  "name": "6",
  "manager": "Мец Иван Сергеевич",
  "district": "ЮАО",
  "phones": [
    {
      "name": "Руководитель",
      "number": "+7 (495) 620-52-41",
      "_id": {
        "$oid": "68e7f39308b0ee7b2d1b3374"
      }
    }
  ],
  "createdAt": {
    "$date": "2025-10-09T17:40:35.590Z"
  },
  "updatedAt": {
    "$date": "2025-10-09T17:40:35.590Z"
  },
  "__v": 0
},
{
  "_id": {
    "$oid": "68e7f3dd08b0ee7b2d1b33ae"
  },
  "name": "7",
  "manager": "Литвин Максим Стефанович",
  "district": "ЮЗАО",
  "phones": [
    {
      "name": "Руководитель",
      "number": "+7 (495) 421-40-01",
      "_id": {
        "$oid": "68e7f3dd08b0ee7b2d1b33af"
      }
    }
  ],
  "createdAt": {
    "$date": "2025-10-09T17:41:49.619Z"
  },
  "updatedAt": {
    "$date": "2025-10-09T17:41:49.619Z"
  },
  "__v": 0
},
{
  "_id": {
    "$oid": "68e7f3f608b0ee7b2d1b33b9"
  },
  "name": "8",
  "manager": "Гаврилов Дмитрий Юрьевич",
  "district": "ЗАО",
  "phones": [
    {
      "name": "Руководитель",
      "number": "+7 (495) 412-61-40",
      "_id": {
        "$oid": "68e7f3f608b0ee7b2d1b33ba"
      }
    }
  ],
  "createdAt": {
    "$date": "2025-10-09T17:42:14.519Z"
  },
  "updatedAt": {
    "$date": "2025-10-09T17:42:14.519Z"
  },
  "__v": 0
},
{
  "_id": {
    "$oid": "68e7f40e08b0ee7b2d1b33c4"
  },
  "name": "9",
  "manager": "Лебедев Дмитрий Анатольевич",
  "district": "ЦАО",
  "phones": [
    {
      "name": "Руководитель",
      "number": "+7 (499) 255-08-37",
      "_id": {
        "$oid": "68e7f40e08b0ee7b2d1b33c5"
      }
    }
  ],
  "createdAt": {
    "$date": "2025-10-09T17:42:38.836Z"
  },
  "updatedAt": {
    "$date": "2025-10-09T17:42:38.836Z"
  },
  "__v": 0
},
{
  "_id": {
    "$oid": "68e7f42508b0ee7b2d1b33cf"
  },
  "name": "10",
  "manager": "Киреев Сергей Александрович",
  "district": "ТиНАО",
  "phones": [
    {
      "name": "Руководитель",
      "number": "+ 7 (495) 620-52-55",
      "_id": {
        "$oid": "68e7f42508b0ee7b2d1b33d0"
      }
    }
  ],
  "createdAt": {
    "$date": "2025-10-09T17:43:01.573Z"
  },
  "updatedAt": {
    "$date": "2025-10-09T17:43:01.573Z"
  },
  "__v": 0
}]